Metadata-Version: 1.0
Name: akashIsAwesome
Version: 0.0.1
Summary: This is a test library
Home-page: UNKNOWN
Author: Akash
Author-email: akash5gupta5@gmail.com
License: UNKNOWN
Keywords: pip,akash,awesome
Platform: UNKNOWN
